MANIFEST.in
README.rst
bootstrap.py
buildout.cfg
setup.py
zc/__init__.py
zc.zdaemonrecipe.egg-info/PKG-INFO
zc.zdaemonrecipe.egg-info/SOURCES.txt
zc.zdaemonrecipe.egg-info/dependency_links.txt
zc.zdaemonrecipe.egg-info/entry_points.txt
zc.zdaemonrecipe.egg-info/namespace_packages.txt
zc.zdaemonrecipe.egg-info/not-zip-safe
zc.zdaemonrecipe.egg-info/requires.txt
zc.zdaemonrecipe.egg-info/top_level.txt
zc/zdaemonrecipe/README.txt
zc/zdaemonrecipe/__init__.py
zc/zdaemonrecipe/tests.py